crisp_t/__init__.py
crisp_t/__main__.py
crisp_t/cli.py
crisp_t/cluster.py
crisp_t/corpuscli.py
crisp_t/csv.py
crisp_t/embedding_linker.py
crisp_t/graph.py
crisp_t/ml.py
crisp_t/network.py
crisp_t/read_data.py
crisp_t/semantic.py
crisp_t/sentiment.py
crisp_t/tdabm.py
crisp_t/temporal.py
crisp_t/text.py
crisp_t/utils.py
crisp_t/visualize.py
crisp_t/vizcli.py
crisp_t/helpers/__init__.py
crisp_t/helpers/analyzer.py
crisp_t/helpers/initializer.py
crisp_t/helpers/clib/__init__.py
crisp_t/helpers/clib/cache.py
crisp_t/helpers/clib/executor.py
crisp_t/helpers/clib/ui.py
crisp_t/mcp/__init__.py
crisp_t/mcp/__main__.py
crisp_t/mcp/server.py
crisp_t/mcp/prompts/__init__.py
crisp_t/mcp/prompts/analysis_workflow.txt
crisp_t/mcp/prompts/triangulation_guide.txt
crisp_t/mcp/tools/__init__.py
crisp_t/mcp/tools/column_operations.py
crisp_t/mcp/tools/corpus_filtering.py
crisp_t/mcp/tools/corpus_management.py
crisp_t/mcp/tools/data_analysis.py
crisp_t/mcp/tools/dataframe_operations.py
crisp_t/mcp/tools/embedding_linking.py
crisp_t/mcp/tools/misc_tools.py
crisp_t/mcp/tools/ml_tools.py
crisp_t/mcp/tools/nlp_analysis.py
crisp_t/mcp/tools/semantic_search.py
crisp_t/mcp/tools/temporal_analysis.py
crisp_t/mcp/tools/topological_analysis.py
crisp_t/mcp/utils/__init__.py
crisp_t/mcp/utils/responses.py
crisp_t/mcp/utils/validators.py
crisp_t/mlib/__init__.py
crisp_t/mlib/config.py
crisp_t/model/__init__.py
crisp_t/model/corpus.py
crisp_t/model/document.py
crisp_t/model/spacy_manager.py
crisp_t-2.2.1.dist-info/METADATA
crisp_t-2.2.1.dist-info/WHEEL
crisp_t-2.2.1.dist-info/entry_points.txt
crisp_t-2.2.1.dist-info/licenses/LICENSE
crisp_t-2.2.1.dist-info/RECORD
