Metadata-Version: 2.4
Name: crisp-t
Version: 2.2.1
Summary: Qualitative Research support tools in Python!
Project-URL: Homepage, https://dermatologist.github.io/crisp-t/
Project-URL: Repository, https://github.com/dermatologist/crisp-t
Project-URL: Documentation, https://dermatologist.github.io/crisp-t/
Author-email: Bell Eapen <github_public@gulfdoctor.net>
License-File: LICENSE
Keywords: python
Classifier: Development Status :: 4 - Beta
Classifier: Intended Audience :: Science/Research
Classifier: Operating System :: OS Independent
Classifier: Programming Language :: Python
Classifier: Programming Language :: Python :: 3
Classifier: Programming Language :: Python :: 3.11
Classifier: Programming Language :: Python :: 3.12
Classifier: Topic :: Scientific/Engineering :: Information Analysis
Classifier: Topic :: Scientific/Engineering :: Medical Science Apps.
Classifier: Topic :: Software Development :: Libraries :: Python Modules
Requires-Python: <4.0,>=3.10
Requires-Dist: chromadb
Requires-Dist: click
Requires-Dist: gensim
Requires-Dist: matplotlib
Requires-Dist: mcp
Requires-Dist: mlxtend
Requires-Dist: networkx
Requires-Dist: pandas
Requires-Dist: pip
Requires-Dist: pydantic
Requires-Dist: pyldavis
Requires-Dist: pypdf
Requires-Dist: requests
Requires-Dist: seaborn
Requires-Dist: spacy
Requires-Dist: tabulate
Requires-Dist: textacy
Requires-Dist: tqdm
Requires-Dist: vadersentiment
Requires-Dist: wordcloud
Provides-Extra: ml
Requires-Dist: imbalanced-learn; extra == 'ml'
Requires-Dist: scikit-learn; extra == 'ml'
Requires-Dist: torch; extra == 'ml'
Provides-Extra: xg
Requires-Dist: xgboost; extra == 'xg'
